mongotail/__init__.py
mongotail/conn.py
mongotail/err.py
mongotail/jsondec.py
mongotail/mongotail.py
mongotail/out.py
mongotail-3.1.1.dist-info/AUTHORS.rst
mongotail-3.1.1.dist-info/COPYING
mongotail-3.1.1.dist-info/METADATA
mongotail-3.1.1.dist-info/WHEEL
mongotail-3.1.1.dist-info/entry_points.txt
mongotail-3.1.1.dist-info/top_level.txt
mongotail-3.1.1.dist-info/RECORD
