Metadata-Version: 2.1
Name: mongotail
Version: 3.1.1
Summary: Mongotail, Log all MongoDB queries in a "tail"able way.
Home-page: https://github.com/mrsarm/mongotail
Download-URL: https://github.com/mrsarm/mongotail/tarball/3.1.1
Author: Mariano Ruiz
Author-email: mrsarm@gmail.com
License: GPL-3
Platform: any
Classifier: Development Status :: 5 - Production/Stable
Classifier: Environment :: Console
Classifier: Intended Audience :: Developers
Classifier: Intended Audience :: System Administrators
Classifier: Topic :: Database
Classifier: Topic :: Utilities
Classifier: Topic :: Terminals
Classifier: License :: Public Domain
Classifier: License :: OSI Approved :: GNU General Public License (GPL)
Classifier: Operating System :: OS Independent
Classifier: Programming Language :: Python
Classifier: Programming Language :: Python :: 2.7
Classifier: Programming Language :: Python :: 3
Classifier: Programming Language :: Python :: 3.6
Classifier: Programming Language :: Python :: 3.7
Classifier: Programming Language :: Python :: 3.8
Classifier: Programming Language :: Python :: 3.9
Classifier: Programming Language :: Python :: 3.10
License-File: COPYING
License-File: AUTHORS.rst
Requires-Dist: pymongo[srv] (<5.0.0,>=3.12)
Requires-Dist: res-address (<3.0.0,>=2.0.0)
